scrapy_processors/__init__.py
scrapy_processors/base.py
scrapy_processors/collections.py
scrapy_processors/common.py
scrapy_processors/multi_values.py
scrapy_processors/single_value.py
scrapy_processors-2.0.5.dist-info/LICENSE
scrapy_processors-2.0.5.dist-info/METADATA
scrapy_processors-2.0.5.dist-info/WHEEL
scrapy_processors-2.0.5.dist-info/RECORD
