Metadata-Version: 2.1
Name: scrapy-processors
Version: 2.0.5
Summary: Provides processors for the itemloaders package, commonly used with scrapy.
Home-page: https://github.com/nicholas-mischke/scrapy-processors
License: MIT
Keywords: scrapy,itemloaders
Author: Nicholas Mischke
Author-email: nmischkework@proton.me
Requires-Python: >=3.9.0,<4.0.0
Classifier: License :: OSI Approved :: MIT License
Classifier: Programming Language :: Python :: 3
Classifier: Programming Language :: Python :: 3.9
Classifier: Programming Language :: Python :: 3.10
Classifier: Programming Language :: Python :: 3.11
Classifier: Programming Language :: Python :: 3.12
Requires-Dist: beautifulsoup4 (>=4.12.2,<5.0.0)
Requires-Dist: dateparser (>=1.1.8,<2.0.0)
Requires-Dist: emoji (>=2.2.0,<3.0.0)
Requires-Dist: itemloaders (>=1.1.0,<2.0.0)
Requires-Dist: miscellaneous-utils (>=0.3.9,<0.4.0)
Requires-Dist: pendulum (>=3.0.0,<4.0.0)
Requires-Dist: phonenumbers (>=8.13.17,<9.0.0)
Requires-Dist: price-parser (>=0.3.4,<0.4.0)
Requires-Dist: pytz (>=2023.3,<2024.0)
Requires-Dist: tzlocal (>=5.0.1,<6.0.0)
Project-URL: Repository, https://github.com/nicholas-mischke/scrapy-processors
